ioc_finder/__init__.py
ioc_finder/data.py
ioc_finder/ioc_finder.py
ioc_finder/ioc_grammars.py
tests/find_iocs_cases/__init__.py
tests/find_iocs_cases/asns.py
tests/find_iocs_cases/attack_data.py
tests/find_iocs_cases/coins.py
tests/find_iocs_cases/cves.py
tests/find_iocs_cases/domains.py
tests/find_iocs_cases/email.py
tests/find_iocs_cases/feature__included_ioc_types.py
tests/find_iocs_cases/file_paths.py
tests/find_iocs_cases/hashes.py
tests/find_iocs_cases/ids.py
tests/find_iocs_cases/ip_addr.py
tests/find_iocs_cases/mac_addr.py
tests/find_iocs_cases/registry_keys.py
tests/find_iocs_cases/tlp_labels.py
tests/find_iocs_cases/urls.py
tests/find_iocs_cases/user_agents.py
ioc_finder-7.3.0.dist-info/COPYING
ioc_finder-7.3.0.dist-info/COPYING.LESSER
ioc_finder-7.3.0.dist-info/METADATA
ioc_finder-7.3.0.dist-info/WHEEL
ioc_finder-7.3.0.dist-info/entry_points.txt
ioc_finder-7.3.0.dist-info/top_level.txt
ioc_finder-7.3.0.dist-info/zip-safe
ioc_finder-7.3.0.dist-info/RECORD
